MANIFEST.in
README.txt
setup.cfg
setup.py
wwitzel_scaffolds/__init__.py
wwitzel_scaffolds.egg-info/PKG-INFO
wwitzel_scaffolds.egg-info/SOURCES.txt
wwitzel_scaffolds.egg-info/dependency_links.txt
wwitzel_scaffolds.egg-info/entry_points.txt
wwitzel_scaffolds.egg-info/not-zip-safe
wwitzel_scaffolds.egg-info/requires.txt
wwitzel_scaffolds.egg-info/top_level.txt
wwitzel_scaffolds/ww3_pymongo/CHANGES.txt_tmpl
wwitzel_scaffolds/ww3_pymongo/MANIFEST.in_tmpl
wwitzel_scaffolds/ww3_pymongo/README.txt_tmpl
wwitzel_scaffolds/ww3_pymongo/config.rb_tmpl
wwitzel_scaffolds/ww3_pymongo/development.ini_tmpl
wwitzel_scaffolds/ww3_pymongo/production.ini_tmpl
wwitzel_scaffolds/ww3_pymongo/setup.cfg_tmpl
wwitzel_scaffolds/ww3_pymongo/setup.py_tmpl
wwitzel_scaffolds/ww3_pymongo/+package+/__init__.py_tmpl
wwitzel_scaffolds/ww3_pymongo/+package+/core/__init__.py_tmpl
wwitzel_scaffolds/ww3_pymongo/+package+/core/interfaces.py
wwitzel_scaffolds/ww3_pymongo/+package+/core/model.py_tmpl
wwitzel_scaffolds/ww3_pymongo/+package+/core/routes.py_tmpl
wwitzel_scaffolds/ww3_pymongo/+package+/core/templates/admin.mako_tmpl
wwitzel_scaffolds/ww3_pymongo/+package+/core/templates/index.mako_tmpl
wwitzel_scaffolds/ww3_pymongo/+package+/core/templates/login.mako_tmpl
wwitzel_scaffolds/ww3_pymongo/+package+/core/views/__init__.py_tmpl
wwitzel_scaffolds/ww3_pymongo/+package+/example/README.txt_tmpl
wwitzel_scaffolds/ww3_pymongo/+package+/example/__init__.py_tmpl
wwitzel_scaffolds/ww3_pymongo/+package+/example/model.py_tmpl
wwitzel_scaffolds/ww3_pymongo/+package+/example/routes.py_tmpl
wwitzel_scaffolds/ww3_pymongo/+package+/example/schema.py
wwitzel_scaffolds/ww3_pymongo/+package+/example/templates/example.mako
wwitzel_scaffolds/ww3_pymongo/+package+/example/templates/index.mako
wwitzel_scaffolds/ww3_pymongo/+package+/example/views/__init__.py_tmpl
wwitzel_scaffolds/ww3_pymongo/+package+/scripts/__init__.py
wwitzel_scaffolds/ww3_pymongo/+package+/scripts/initialize.py_tmpl
wwitzel_scaffolds/ww3_pymongo/+package+/security/__init__.py_tmpl
wwitzel_scaffolds/ww3_pymongo/+package+/static/images/README
wwitzel_scaffolds/ww3_pymongo/+package+/static/javascripts/foundation/foundation.abide.js
wwitzel_scaffolds/ww3_pymongo/+package+/static/javascripts/foundation/foundation.alerts.js
