Metadata-Version: 1.1
Name: wwitzel-scaffolds
Version: 0.5
Summary: Custom scaffolds for the Pyramid web application development framework
Home-page: https://github.com/wwitzel3/wwitzel_scaffolds
Author: Wayne Witzel III
Author-email: wayne@pieceofpy.com
License: BSD-derived (http://www.repoze.org/LICENSE.txt)
Keywords: web wsgi pylons pyramid
Platform: UNKNOWN
Classifier: Intended Audience :: Developers
Classifier: Programming Language :: Python
Classifier: Framework :: Pylons
Classifier: Topic :: Internet :: WWW/HTTP
Classifier: Topic :: Internet :: WWW/HTTP :: WSGI
Classifier: License :: Repoze Public License
